seaplayer_audio/__init__.py
seaplayer_audio/__main__.py
seaplayer_audio/_types.py
seaplayer_audio/audiosources/__init__.py
seaplayer_audio/audiosources/fileaudiosource.py
seaplayer_audio/audiosources/urlaudiosource.py
seaplayer_audio/audiosources/urlio.py
seaplayer_audio/base/__init__.py
seaplayer_audio/base/audiosource.py
seaplayer_audio/base/sndstreamer.py
seaplayer_audio/base/streamer.py
seaplayer_audio/functions.py
seaplayer_audio/streamers/__init__.py
seaplayer_audio/streamers/callbackstreamersnd.py
seaplayer_audio/streamers/threadstreamersnd.py
seaplayer_audio-0.5.12.dist-info/LICENSE
seaplayer_audio-0.5.12.dist-info/METADATA
seaplayer_audio-0.5.12.dist-info/WHEEL
seaplayer_audio-0.5.12.dist-info/RECORD
