Metadata-Version: 2.1
Name: seaplayer-audio
Version: 0.5.12
Summary: A library for async/sync playback audio.
Home-page: https://github.com/romanin-rf/seaplayer-audio
License: MIT
Keywords: seaplayer,audio,sound,stream,play,playback,read,io
Author: Romanin
Author-email: 60302782+romanin-rf@users.noreply.github.com
Requires-Python: >=3.10
Classifier: Framework :: AsyncIO
Classifier: License :: OSI Approved :: MIT License
Classifier: Operating System :: MacOS
Classifier: Operating System :: Microsoft :: Windows :: Windows 10
Classifier: Operating System :: POSIX :: Linux
Classifier: Operating System :: Unix
Classifier: Programming Language :: Python :: 3
Classifier: Programming Language :: Python :: 3.10
Classifier: Programming Language :: Python :: 3.11
Classifier: Programming Language :: Python :: 3.12
Classifier: Programming Language :: Python :: 3.13
Classifier: Topic :: Multimedia :: Sound/Audio
Classifier: Topic :: Multimedia :: Sound/Audio :: Players
Classifier: Topic :: Multimedia :: Sound/Audio :: Players :: MP3
Classifier: Typing :: Typed
Provides-Extra: dev
Requires-Dist: mutagen (>=1.47.0,<2.0.0)
Requires-Dist: numpy (>=2.1.3,<3.0.0)
Requires-Dist: pillow (>=11.0.0,<12.0.0)
Requires-Dist: python-dateutil (>=2.9.0.post0,<3.0.0)
Requires-Dist: sounddevice (>=0.5.1,<0.6.0)
Requires-Dist: soundfile (>=0.12.1,<0.13.0)
Requires-Dist: typing-extensions (>=4.12.2,<5.0.0)
Project-URL: Repository, https://github.com/romanin-rf/seaplayer-audio
